repodynamics/__init__.py
repodynamics/__main__.py
repodynamics/commit.py
repodynamics/datatype.py
repodynamics/git.py
repodynamics/hook.py
repodynamics/logger.py
repodynamics/path.py
repodynamics/version.py
repodynamics/_data/db.yaml
repodynamics/_data/example/config.yaml
repodynamics/_data/example/extensions.yaml
repodynamics/_data/example/path.yaml
repodynamics/_data/example/dev/branch.yaml
repodynamics/_data/example/dev/changelog.yaml
repodynamics/_data/example/project/credits.yaml
repodynamics/_data/example/project/intro.yaml
repodynamics/_data/example/project/license.yaml
repodynamics/_data/license/apache_v2.txt
repodynamics/_data/license/apache_v2_notice.txt
repodynamics/_data/license/bsd_2_clause.txt
repodynamics/_data/license/bsd_2_clause_notice.txt
repodynamics/_data/license/bsd_3_clause.txt
repodynamics/_data/license/bsd_3_clause_notice.txt
repodynamics/_data/license/bsl_v1.txt
repodynamics/_data/license/bsl_v1_notice.txt
repodynamics/_data/license/gnu_agpl_v3.txt
repodynamics/_data/license/gnu_agpl_v3_notice.txt
repodynamics/_data/license/gnu_gpl_v3.txt
repodynamics/_data/license/gnu_gpl_v3_notice.txt
repodynamics/_data/license/mit.txt
repodynamics/_data/license/mit_notice.txt
repodynamics/_data/license/mozilla_v2.txt
repodynamics/_data/license/mozilla_v2_notice.txt
repodynamics/_data/license/unlicense.txt
repodynamics/_data/license/unlicense_notice.txt
repodynamics/_data/schema/config.yaml
repodynamics/_data/schema/extensions.yaml
repodynamics/_data/schema/path.yaml
repodynamics/_data/schema/custom/custom.yaml
repodynamics/_data/schema/dev/branch.yaml
repodynamics/_data/schema/dev/changelog.yaml
repodynamics/_data/schema/dev/commit.yaml
repodynamics/_data/schema/dev/discussion.yaml
repodynamics/_data/schema/dev/issue.yaml
repodynamics/_data/schema/dev/label.yaml
repodynamics/_data/schema/dev/maintainer.yaml
repodynamics/_data/schema/dev/pull.yaml
repodynamics/_data/schema/dev/repo.yaml
repodynamics/_data/schema/dev/tag.yaml
RepoDynamics-0.0.0.dev245.dist-info/METADATA
RepoDynamics-0.0.0.dev245.dist-info/WHEEL
RepoDynamics-0.0.0.dev245.dist-info/top_level.txt
RepoDynamics-0.0.0.dev245.dist-info/RECORD
