Metadata-Version: 2.1
Name: RepoDynamics
Version: 0.0.0.dev245
Requires-Python: >=3.10
Requires-Dist: packaging <24,>=23.2
Requires-Dist: pre-commit ==3.3.3
Requires-Dist: markitup
Requires-Dist: jsonschema <5,>=4.19
Requires-Dist: pylinks
Requires-Dist: trove-classifiers
Requires-Dist: readme-renderer[md]
Requires-Dist: ruamel.yaml <0.18,>=0.17.32
Requires-Dist: ruamel.yaml.string <1,>=0.1.1
Requires-Dist: tomlkit <0.12,>=0.11.8
Requires-Dist: pycolorit
Requires-Dist: pybadger
Requires-Dist: github-contexts
